fuzzydata/__init__.py
fuzzydata/cli.py
fuzzydata/clients/__init__.py
fuzzydata/clients/modin.py
fuzzydata/clients/pandas.py
fuzzydata/clients/sqlite.py
fuzzydata/core/__init__.py
fuzzydata/core/artifact.py
fuzzydata/core/generator.py
fuzzydata/core/operation.py
fuzzydata/core/workflow.py
fuzzydata/core/config/groupable_cols.txt
fuzzydata/core/config/joinable_cols.txt
fuzzydata/core/config/numeric_cols.txt
fuzzydata/core/config/removed.txt
fuzzydata/core/config/string_cols.txt
fuzzydata-0.0.11.data/scripts/fuzzydata
tests/__init__.py
tests/conftest.py
tests/test_cli.py
tests/core/__init__.py
tests/core/test_artifact.py
tests/core/test_generator.py
tests/core/test_operation.py
tests/core/test_workflow.py
fuzzydata-0.0.11.dist-info/LICENSE
fuzzydata-0.0.11.dist-info/METADATA
fuzzydata-0.0.11.dist-info/WHEEL
fuzzydata-0.0.11.dist-info/top_level.txt
fuzzydata-0.0.11.dist-info/RECORD
