Metadata-Version: 2.1
Name: fuzzydata
Version: 0.0.11
Summary: Fuzzy Data Benchmark
Home-page: https://github.com/suhailrehman/fuzzydata
Author: Suhail Rehman
Author-email: suhailrehman@gmail.com
Project-URL: Bug Tracker, https://github.com/suhailrehman/fuzzydata/issues
Classifier: Programming Language :: Python :: 3
Classifier: License :: OSI Approved :: MIT License
Classifier: Operating System :: OS Independent
Requires-Python: >=3.7
License-File: LICENSE
Requires-Dist: faker >=13.3.0
Requires-Dist: pandas >=1.4.0
Requires-Dist: networkx >=2.7
Requires-Dist: SQLAlchemy >=2.0.0
Provides-Extra: modin
Requires-Dist: modin[all] >=0.13.2 ; extra == 'modin'
